inf_STT/__init__.py
inf_stt-0.1.dist-info/METADATA
inf_stt-0.1.dist-info/WHEEL
inf_stt-0.1.dist-info/top_level.txt
inf_stt-0.1.dist-info/RECORD
